sc_credit_card/__init__.py
sc_credit_card/main.py
sc_credit_card/analyzer/__init__.py
sc_credit_card/analyzer/batch_status.py
sc_credit_card/analyzer/batch_type.py
sc_credit_card/analyzer/cc_apply_status_analyzer.py
sc_credit_card/analyzer/cc_pad_apply_status_analyzer.py
sc_credit_card/db/__init__.py
sc_credit_card/db/cc_sql.py
sc_credit_card/db/db_module.py
sc_credit_card/tests/__init__.py
sc_credit_card/tests/sample_config/production.yml
sc_credit_card_apply_status_analysis-0.0.1.dist-info/LICENSE
sc_credit_card_apply_status_analysis-0.0.1.dist-info/METADATA
sc_credit_card_apply_status_analysis-0.0.1.dist-info/WHEEL
sc_credit_card_apply_status_analysis-0.0.1.dist-info/entry_points.txt
sc_credit_card_apply_status_analysis-0.0.1.dist-info/top_level.txt
sc_credit_card_apply_status_analysis-0.0.1.dist-info/RECORD
